endstone_economy_pilot_lite/__init__.py
endstone_economy_pilot_lite/config.py
endstone_economy_pilot_lite/database_controller.py
endstone_economy_pilot_lite/main.py
endstone_economy_pilot_lite-0.0.4.dist-info/METADATA
endstone_economy_pilot_lite-0.0.4.dist-info/WHEEL
endstone_economy_pilot_lite-0.0.4.dist-info/entry_points.txt
endstone_economy_pilot_lite-0.0.4.dist-info/RECORD
