Metadata-Version: 2.3
Name: endstone-economy_pilot_lite
Version: 0.0.4
Summary: Economy Pilot Lite api for Endstone servers!
